[
  {
    "title": "Common Misconceptions about Obesity",
    "doi": "10.5040/9798400692581.0008",
    "url": "https://doi.org/10.5040/9798400692581.0008",
    "year": 2019,
    "source": "crossref",
    "score": 0.8
  },
  {
    "title": "Common Misconceptions about Autism",
    "doi": "10.5040/9798765110515.0007",
    "url": "https://doi.org/10.5040/9798765110515.0007",
    "year": 2024,
    "source": "crossref",
    "score": 0.8
  },
  {
    "title": "Common Misconceptions about Exercise",
    "doi": "10.5040/9798216185000.0008",
    "url": "https://doi.org/10.5040/9798216185000.0008",
    "year": 2022,
    "source": "crossref",
    "score": 0.8
  },
  {
    "title": "Common Misconceptions about Yoga",
    "doi": "10.5040/9798216039952.0008",
    "url": "https://doi.org/10.5040/9798216039952.0008",
    "year": 2021,
    "source": "crossref",
    "score": 0.8
  },
  {
    "title": "SHAREABLE RESOURCE",
    "doi": "10.1249/fit.0000000000001034",
    "url": "https://doi.org/10.1249/fit.0000000000001034",
    "year": 2025,
    "source": "crossref",
    "score": 0.8
  },
  {
    "title": "Common Misconceptions about Depression",
    "doi": "10.5040/9798400639289.0008",
    "url": "https://doi.org/10.5040/9798400639289.0008",
    "year": 2019,
    "source": "crossref",
    "score": 0.8
  },
  {
    "title": "Common Misconceptions about Food Labels",
    "doi": "10.5040/9798400652691.0007",
    "url": "https://doi.org/10.5040/9798400652691.0007",
    "year": 2019,
    "source": "crossref",
    "score": 0.8
  },
  {
    "title": "Common Misconceptions about Substance Abuse",
    "doi": "10.5040/9798216021049.0008",
    "url": "https://doi.org/10.5040/9798216021049.0008",
    "year": 2018,
    "source": "crossref",
    "score": 0.8
  },
  {
    "title": "Common Misconceptions about Eating Disorders",
    "doi": "10.5040/9798400643354.0008",
    "url": "https://doi.org/10.5040/9798400643354.0008",
    "year": 2018,
    "source": "crossref",
    "score": 0.8
  },
  {
    "title": "Common Misconceptions about Teen Stress",
    "doi": "10.5040/9798216023821.0007",
    "url": "https://doi.org/10.5040/9798216023821.0007",
    "year": 2020,
    "source": "crossref",
    "score": 0.8
  },
  {
    "title": "Common Misconceptions about Sexual Harassment",
    "doi": "10.5040/9798216013600.0008",
    "url": "https://doi.org/10.5040/9798216013600.0008",
    "year": 2021,
    "source": "crossref",
    "score": 0.8
  },
  {
    "title": "Common Misconceptions about Healthy Sleep",
    "doi": "10.5040/9798216171720.0008",
    "url": "https://doi.org/10.5040/9798216171720.0008",
    "year": 2023,
    "source": "crossref",
    "score": 0.8
  },
  {
    "title": "Common Misconceptions about Grief and Loss",
    "doi": "10.5040/9798400659621.0007",
    "url": "https://doi.org/10.5040/9798400659621.0007",
    "year": 2020,
    "source": "crossref",
    "score": 0.8
  },
  {
    "title": "Common Misconceptions about Trauma and Resilience",
    "doi": "10.5040/9798216027355.0007",
    "url": "https://doi.org/10.5040/9798216027355.0007",
    "year": 2021,
    "source": "crossref",
    "score": 0.8
  },
  {
    "title": "Common Misconceptions about Therapy and Counseling",
    "doi": "10.5040/9798216025412.0008",
    "url": "https://doi.org/10.5040/9798216025412.0008",
    "year": 2019,
    "source": "crossref",
    "score": 0.8
  },
  {
    "title": "Common Misconceptions about Epidemics and Pandemics",
    "doi": "10.5040/9798765110492.0006",
    "url": "https://doi.org/10.5040/9798765110492.0006",
    "year": 2024,
    "source": "crossref",
    "score": 0.8
  },
  {
    "title": "Common Misconceptions about Food Allergies and Sensitivities",
    "doi": "10.5040/9798400652219.0007",
    "url": "https://doi.org/10.5040/9798400652219.0007",
    "year": 2019,
    "source": "crossref",
    "score": 0.8
  },
  {
    "title": "Ten Common Questions About Hypertrophic Cardiomyopathy...and Misconceptions",
    "doi": "10.1097/01.crd.0000152520.82421.09",
    "url": "https://doi.org/10.1097/01.crd.0000152520.82421.09",
    "year": 2005,
    "source": "crossref",
    "score": 0.8
  },
  {
    "title": "Common questions and misconceptions about creatine supplementation: what does the scientific evidence really show?",
    "doi": "10.1186/s12970-021-00412-w",
    "url": "https://doi.org/10.1186/s12970-021-00412-w",
    "year": 2021,
    "source": "crossref",
    "score": 0.8
  },
  {
    "title": "Common-sense views and misconceptions about psychology",
    "doi": "10.4324/9780203769454-4",
    "url": "https://doi.org/10.4324/9780203769454-4",
    "year": 2013,
    "source": "crossref",
    "score": 0.8
  },
  {
    "title": "Some Common Misconceptions about STEM Education",
    "doi": "10.31229/osf.io/qkchd",
    "url": "https://doi.org/10.31229/osf.io/qkchd",
    "year": 2019,
    "source": "crossref",
    "score": 0.8
  },
  {
    "title": "[RETRACTED] 14 Common Misconceptions About K1 Keto Life v1",
    "doi": "10.17504/protocols.io.n2bvj6qw5lk5/v1",
    "url": "https://doi.org/10.17504/protocols.io.n2bvj6qw5lk5/v1",
    "year": 2022,
    "source": "crossref",
    "score": 0.8
  },
  {
    "title": "Misconceptions about cancer screening may be common among women",
    "doi": "10.1037/e556182006-014",
    "url": "https://doi.org/10.1037/e556182006-014",
    "year": 2005,
    "source": "crossref",
    "score": 0.8
  },
  {
    "title": "Common Misconceptions About Language Learning",
    "doi": "10.2307/jj.27710957.7",
    "url": "https://doi.org/10.2307/jj.27710957.7",
    "year": 2003,
    "source": "crossref",
    "score": 0.8
  },
  {
    "title": "Common Misconceptions about Nidotherapy",
    "doi": "10.1017/9781911623403.014",
    "url": "https://doi.org/10.1017/9781911623403.014",
    "year": 2018,
    "source": "crossref",
    "score": 0.8
  },
  {
    "title": "The danger of innocence : common sense beliefs and misconceptions about false confessions",
    "doi": "10.26481/dis.20141215js",
    "url": "https://doi.org/10.26481/dis.20141215js",
    "year": null,
    "source": "crossref",
    "score": 0.8
  },
  {
    "title": "Four Common Misconceptions About Copyright Piracy",
    "doi": "10.2139/ssrn.443160",
    "url": "https://doi.org/10.2139/ssrn.443160",
    "year": 2003,
    "source": "crossref",
    "score": 0.8
  },
  {
    "title": "Three common misconceptions about the FDA",
    "doi": "10.1097/01.jaa.0000552731.88186.5f",
    "url": "https://doi.org/10.1097/01.jaa.0000552731.88186.5f",
    "year": 2019,
    "source": "crossref",
    "score": 0.8
  },
  {
    "title": "Most common misconceptions about transradial approach in interventional oncology: results of an international survey",
    "doi": "10.26226/morressier.5fbe94fe1199233b624ee636",
    "url": "https://doi.org/10.26226/morressier.5fbe94fe1199233b624ee636",
    "year": 2020,
    "source": "crossref",
    "score": 0.8
  },
  {
    "title": "Misconceptions About Asking Questions",
    "doi": "10.4324/9781003175674-18",
    "url": "https://doi.org/10.4324/9781003175674-18",
    "year": 2021,
    "source": "crossref",
    "score": 0.8
  }
]